{
  "$schema": "https://json-schema.org/draft-07/schema",
  "$id": "https://json-schema.org/draft-07/schema",
  "title": "GenerateApiLibSources builder",
  "description": "",
  "type": "object",
  "properties": {
    "generator": {
      "type": "string",
      "description": "The openapitools generator you want to use",
      "default": "typescript-fetch"
    },
    "sourceSpecLib": {
      "type": "string",
      "description": "The workspace lib where the source OpenAPI spec file is located"
    },
    "sourceSpecFileRelativePath": {
      "type": "string",
      "description": "The name of the source OpenAPI spec file, and its path relative to the root of the `sourceSpecLib` project"
    }
  },
  "required": []
}
